{
  "TND-2026-001": {
    "tenderId": "TND-2026-001",
    "tenderTitle": "Smart City Road Infrastructure — Phase 2",
    "deadline": "2026-05-20T17:00:00Z",
    "deadlinePassed": true,
    "evaluationWeights": { "price":40,"financial":15,"experience":15,"performance":10,"technical":10,"compliance":5,"proposal":5 },
    "bids": [
      {
        "bidderId": "VEN-001",
        "companyName": "Infra Build Pvt Ltd",
        "walletAddress": "0xAbCdEf0011223344556677889900aAbCdEf0011",
        "bidHash": "QmInfraBidHash000000000000000000000000000001",
        "submittedAt": "2026-05-18T14:23:00Z",
        "price": 4750000,
        "scores": { "price":85, "financial":78, "experience":82, "performance":74, "technical":80, "compliance":90, "proposal":70 },
        "totalScore": 81.6,
        "status": "winner",
        "documents": [{ "name":"Technical Proposal", "ipfsHash":"QmInfraDoc1" }, { "name":"Financial Bid","ipfsHash":"QmInfraDoc2" }]
      },
      {
        "bidderId": "VEN-002",
        "companyName": "BuildRight Constructions",
        "walletAddress": "0xBbCcDd11223344556677889900BbCcDd11223344",
        "bidHash": "QmBuildRightBidHash00000000000000000000000002",
        "submittedAt": "2026-05-18T15:10:00Z",
        "price": 4850000,
        "scores": { "price":80, "financial":75, "experience":80, "performance":72, "technical":78, "compliance":85, "proposal":68 },
        "totalScore": 78.9,
        "status": "evaluated",
        "documents": [{ "name":"Tech","ipfsHash":"QmBRDoc1" }]
      },
      {
        "bidderId": "VEN-003",
        "companyName": "Skyline Engineers",
        "walletAddress": "0xCcDdEe22334455667788990011CcDdEe22334455",
        "bidHash": "QmSkylineBidHash0000000000000000000000000003",
        "submittedAt": "2026-05-19T09:05:00Z",
        "price": 4900000,
        "scores": { "price":78, "financial":70, "experience":76, "performance":70, "technical":75, "compliance":80, "proposal":65 },
        "totalScore": 75.8,
        "status": "evaluated",
        "documents": [{ "name":"Tech","ipfsHash":"QmSkyDoc1" }]
      },
      {
        "bidderId": "VEN-004",
        "companyName": "Faulty Works",
        "walletAddress": "0xDdEeFf33445566778899001122DdEeFf33445566",
        "bidHash": "QmFaultyBidHash0000000000000000000000000004",
        "submittedAt": "2026-05-19T12:30:00Z",
        "price": 4700000,
        "scores": null,
        "totalScore": null,
        "status": "disqualified",
        "disqualificationReason": "GST certificate expired",
        "documents": []
      }
    ]
  },
  "TC-MH-2024-883": [
    {
      "bidderId": "vendor-001",
      "walletAddress": "0x41b2d3e4f5a6c7d8e9f00112233445566778899a",
      "submittedAt": "2026-05-14T09:20:00Z",
      "encrypted": false,
      "price": 4150000000,
      "scores": {
        "price": 8,
        "financial": 9,
        "experience": 8,
        "performance": 7,
        "technical": 9,
        "compliance": 10,
        "proposal": 8
      }
    },
    {
      "bidderId": "vendor-003",
      "walletAddress": "0x8f7e6d5c4b3a29181716151413121110aabbccdd",
      "submittedAt": "2026-05-14T10:40:00Z",
      "encrypted": false,
      "price": 4020000000,
      "scores": {
        "price": 9,
        "financial": 8,
        "experience": 9,
        "performance": 8,
        "technical": 8,
        "compliance": 10,
        "proposal": 9
      }
    },
    {
      "bidderId": "vendor-006",
      "walletAddress": "0x1234abcd5678ef901234abcd5678ef901234abcd",
      "submittedAt": "2026-05-14T12:05:00Z",
      "encrypted": true,
      "price": 3895000000,
      "scores": {
        "price": 0,
        "financial": 0,
        "experience": 0,
        "performance": 0,
        "technical": 0,
        "compliance": 0,
        "proposal": 0
      }
    }
  ],
  "TC-DL-2024-102": [
    {
      "bidderId": "vendor-002",
      "walletAddress": "0xaabbccddeeff0011223344556677889900112233",
      "submittedAt": "2026-04-27T13:12:00Z",
      "encrypted": false,
      "price": 1180000000,
      "scores": {
        "price": 10,
        "financial": 8,
        "experience": 9,
        "performance": 7,
        "technical": 9,
        "compliance": 9,
        "proposal": 8
      }
    },
    {
      "bidderId": "vendor-005",
      "walletAddress": "0x99887766554433221100ffeeddccbbaa99887766",
      "submittedAt": "2026-04-27T15:40:00Z",
      "encrypted": false,
      "price": 1215000000,
      "scores": {
        "price": 9,
        "financial": 9,
        "experience": 8,
        "performance": 8,
        "technical": 8,
        "compliance": 10,
        "proposal": 9
      }
    }
  ],
  "TC-RJ-2024-405": [
    {
      "bidderId": "vendor-004",
      "walletAddress": "0x1111222233334444555566667777888899990000",
      "submittedAt": "2026-03-10T08:30:00Z",
      "encrypted": false,
      "price": 2045000000,
      "scores": {
        "price": 8,
        "financial": 8,
        "experience": 8,
        "performance": 9,
        "technical": 9,
        "compliance": 10,
        "proposal": 8
      }
    },
    {
      "bidderId": "vendor-009",
      "walletAddress": "0xffeeddccbbaa99887766554433221100ffeeddcc",
      "submittedAt": "2026-03-10T10:25:00Z",
      "encrypted": false,
      "price": 1980000000,
      "scores": {
        "price": 9,
        "financial": 9,
        "experience": 9,
        "performance": 8,
        "technical": 9,
        "compliance": 10,
        "proposal": 9
      }
    }
  ]
}